README.txt
setup.py
hyperbmp/__init__.py
hyperbmp/click.js
hyperbmp/edit.py
hyperbmp/lib.js
hyperbmp/lib.py
hyperbmp/props.py
hyperbmp/read.py
hyperbmp/wsgi.py
hyperbmp.egg-info/PKG-INFO
hyperbmp.egg-info/SOURCES.txt
hyperbmp.egg-info/dependency_links.txt
hyperbmp.egg-info/entry_points.txt
hyperbmp.egg-info/not-zip-safe
hyperbmp.egg-info/requires.txt
hyperbmp.egg-info/top_level.txt