Metadata-Version: 1.0
Name: hyperbmp
Version: 0.2
Summary: display and edit hyperbitmaps
Home-page: UNKNOWN
Author: UNKNOWN
Author-email: UNKNOWN
License: UNKNOWN
Platform: UNKNOWN
